turboparse/__init__.py
turboparse/common_parser.py
turboparse/freeh_parser.py
turboparse/line_parser.py
turboparse/parse.py
turboparse/parse_turbo.py
turboparse/response_parser.py
turboparse/scf_parser.py
turboparse/section_parser.py
turboparse/stack_iterator.py
turboparse/thermo_parser.py
turboparse-0.1.2.dist-info/LICENSE
turboparse-0.1.2.dist-info/METADATA
turboparse-0.1.2.dist-info/WHEEL
turboparse-0.1.2.dist-info/entry_points.txt
turboparse-0.1.2.dist-info/top_level.txt
turboparse-0.1.2.dist-info/RECORD
