Metadata-Version: 2.1
Name: turboparse
Version: 0.1.2
Summary: Parse turbomole outputs and output json or yaml file
Home-page: https://gitlab.com/team-parker/turboparse/
Author: Shane M. Parker
Author-email: shane.parker@case.edu
License: MIT
Keywords: Quantum Chemistry
Platform: UNKNOWN
Classifier: Development Status :: 3 - Alpha
Classifier: Intended Audience :: Developers
Classifier: Intended Audience :: Science/Research
Classifier: Topic :: Scientific/Engineering :: Chemistry
Classifier: Topic :: Scientific/Engineering :: Physics
Classifier: License :: OSI Approved :: MIT License
Classifier: Programming Language :: Python :: 3.6
Requires-Dist: pyyaml
